mapfactory/__init__.py
mapfactory-0.1.0.dist-info/LICENSE
mapfactory-0.1.0.dist-info/METADATA
mapfactory-0.1.0.dist-info/WHEEL
mapfactory-0.1.0.dist-info/RECORD
